dockercomposeHelp/__init__.py
dockercomposeHelp/compose.py
dockercomposeHelp-1.0.0.dist-info/LICENSE
dockercomposeHelp-1.0.0.dist-info/METADATA
dockercomposeHelp-1.0.0.dist-info/WHEEL
dockercomposeHelp-1.0.0.dist-info/top_level.txt
dockercomposeHelp-1.0.0.dist-info/RECORD
