Metadata-Version: 2.1
Name: dockercomposeHelp
Version: 1.0.0
Summary: A Python wrapper for generating a compose file
Home-page: https://github.com/ArielLima/dockercomposeHelp
Author: Ariel Lima
Author-email: ariel.lima@gordon.edu
License: UNKNOWN
Platform: UNKNOWN
Classifier: Programming Language :: Python :: 3
Classifier: License :: OSI Approved :: MIT License
Classifier: Operating System :: OS Independent
Requires-Dist: pyyaml
